README.md
setup.py
lj_spider_sql.egg-info/PKG-INFO
lj_spider_sql.egg-info/SOURCES.txt
lj_spider_sql.egg-info/dependency_links.txt
lj_spider_sql.egg-info/entry_points.txt
lj_spider_sql.egg-info/top_level.txt
package/__init__.py
package/lj_sqlpackage.py
package/utils.py
test/__init__.py
test/test.py